LICENSE
MANIFEST.in
README.md
pyproject.toml
setup.cfg
setup.py
csiweb/__init__.py
csiweb/__main__.py
csiweb/utils.py
csiweb/version.py
csiweb.egg-info/PKG-INFO
csiweb.egg-info/SOURCES.txt
csiweb.egg-info/dependency_links.txt
csiweb.egg-info/entry_points.txt
csiweb.egg-info/requires.txt
csiweb.egg-info/top_level.txt
csiweb/cli/__init__.py
csiweb/cli/__main__.py
csiweb/cli/commands/__init__.py
csiweb/cli/commands/main.py
csiweb/cli/commands/simulate.py
csiweb/cli/commands/files/__init__.py
csiweb/cli/commands/files/download.py
csiweb/cli/commands/files/main.py
csiweb/cli/commands/query/__init__.py
csiweb/cli/commands/query/main.py
csiweb/cli/commands/query/publish.py
csiweb/client/__init__.py
csiweb/client/fake/__init__.py
csiweb/client/fake/dataquery-mode-most-recent-p1-25-uri-dl-public.json
systemd/csiweb-mqtt.service