Metadata-Version: 2.1
Name: csiweb
Version: 0.3.0
Summary: Campbell Scientific CR6 Logger Wifi Interface
Home-page: UNKNOWN
Author: Yann Buechau
Author-email: nobodyinperson@gmx.de
License: GPLv3
Keywords: campbell,campbell scientific,campbellsci,csiweb,datalogger,wifi,irgason
Platform: UNKNOWN
Classifier: License :: OSI Approved :: GNU General Public License v3 (GPLv3)
Classifier: Programming Language :: Python :: 3.6
Classifier: Intended Audience :: Science/Research
Classifier: Topic :: Scientific/Engineering
Requires-Python: >=3.5
